{"cameraMode":{"drawMode":0,"name":"Shaded","section":"Shading Mode"},"sceneLighting":true,"audioPlay":false,"sceneViewState":{"m_AlwaysRefresh":false,"showFog":false,"showSkybox":false,"showFlares":false,"showImageEffects":false,"showParticleSystems":false,"showVisualEffectGraphs":false,"m_FxEnabled":true},"in2DMode":false,"pivot":{"x":-3.0927929878234865,"y":6.078779220581055,"z":14.36853313446045},"rotation":{"x":0.0448998361825943,"y":-0.06139935553073883,"z":0.002769637620076537,"w":0.997105598449707},"size":14.618582725524903,"orthographic":true}